{
    "id": 113808543,
    "name": "Chasing Stars",
    "author": "Chayper",
    "creators": [],
    "verifier": "Chayper",
    "verification": "https://youtu.be/EgvpF3IJOWg",
    "desc": "desc",
    "percentToQualify": 100,
    "records": [
         {
            "user": "Breaker",
            "link": "RecordLink",
            "percent": 100,
            "hz": " - "
        },
        {
            "user": "ZircleZ",
            "link": "RecordLink",
            "percent": 100,
            "hz": " - "
        },
        {
            "user": "WKGames",
            "link": "RecordLink",
            "percent": 100,
            "hz": " - "
        },
        {
            "user": "AceK58",
            "link": "RecordLink",
            "percent": 100,
            "hz": " - "
        },
        {
            "user": "Beeshie", 
            "link": "RecordLink",
            "percent": 100,
            "hz": " - "
        },
        {
            "user": "Yoshi", 
            "link": "RecordLink",
            "percent": 100,
            "hz": " - "
        }
    ]
}
