{
    "id": 40820868,
    "name": "Dynamic Glow",
    "author": "The Bread",
    "creators": [],
    "verifier": "The Bread",
    "verification": "https://youtu.be/H8_9uc4lGdM?si=Jj25IRwCUVwd37L-",
    "desc": "desc",
    "tier": "",
    "enjoyment": "",
    "length": "",
    "percentToQualify": 100,
    "password": "Free Copy",
    "records": [
         {
            "user": "Breaker",
            "link": "RecordLink",
            "percent": 100,
            "hz": " - "
        },
        {
            "user": "Appletun21",
            "link": "RecordLink",
            "percent": 100,
            "hz": " - "
        },
        {
            "user": "ZircleZ",
            "link": "RecordLink",
            "percent": 100,
            "hz": " - "
        },
        {
            "user": "WKGames",
            "link": "RecordLink",
            "percent": 100,
            "hz": " - "
        },
        {
            "user": "Wide Shady",
            "percent": 100,
            "hz": " - "
        }
    ]
}
