{ 
    "id": 94679341,
    "name": "ei vai loz",
    "author": "killervn",
    "creators": [],
    "verifier": "killervn",
    "verification": "https://youtu.be/L52-0mYllTo",
    "desc": "Generic flow level (basically Red Haze if the start and end were grayscale). Marks out robot headhitters way too much and decevingly",
    "percentToQualify": 100,
    "records": [
        {
            "user": "Breaker",
            "link": "RecordLink",
            "percent": 100,
            "hz": " - "
        },
        {
            "user": "ZircleZ",
            "link": "RecordLink",
            "percent": 100,
            "hz": " - "
        },   
        {
            "user": "killswitch",
            "link": "RecordLink",
            "percent": 100,
            "hz": " - "
        },
        {
            "user": "DIUSED",
            "link": "RecordLink",
            "percent": 100,
            "hz": " - "
        },
        {
            "user": "Sir_Manface",
            "link": "RecordLink",
            "percent": 100,
            "hz": " - "
        },
        {
            "user": "WKGames",
            "link": "RecordLink",
            "percent": 100,
            "hz": " - "
        },
        {
            "user": "scape167",
            "link": "RecordLink",
            "percent": 100,
            "hz": " - "
        },
        {
            "user": "yuasargd19",
            "link": "RecordLink",
            "percent": 100,
            "hz": " - "
        },
        {
            "user": "InideuX",
            "link": "RecordLink",
            "percent": 100,
            "hz": " - "
        },
        {
            "user": "LifelessComputer",
            "link": "RecordLink",
            "percent": 100,
            "hz": " - "
        },
        {
            "user": "Liverlan",
            "link": "RecordLink",
            "percent": 100,
            "hz": " - "
        },
        {
            "user": "BillCipher74",
            "link": "RecordLink",
            "percent": 100,
            "hz": " - "
        }
    ]
}
