{
    "id": 95288896,
    "name": "Ethereal Lullaby",
    "author": "FadedCat",
    "creators": [],
    "verifier": "FadedCat",
    "verification": "https://youtu.be/aVuAN5sgi6U?si=0ciZHarCT4vlxo0l",
    "desc": "desc",
    "percentToQualify": 100,
    "records": [
        {
            "user": "Breaker", 
            "percent": 100,
            "hz": 60
        },
        {
            "user": "AceK58", 
            "percent": 100,
            "hz": 60
        },
        {
            "user": "ZircleZ",
            "percent": 100,
            "hz": 60
        },
        {
            "user": "WKGames",
            "percent": 100,
            "hz": 60
        },
        {
            "user": "InideuX", 
            "percent": 100,
            "hz": 60
        }
    ]
}
