{
    "id": 113002494,
    "name": "first day (D)",
    "author": "Koshkaht",
    "creators": [],
    "verifier": "Koshkaht",
    "verification": "https://youtu.be/4m3_E7W3NlI",
    "desc": "desc",
    "percentToQualify": 100,
    "password": "Free Copy",
    "records": [
        {
            "user": "Breaker",
            "link": "RecordLink",
            "percent": 100,
            "hz": " - "
        },
        {
            "user": "Starlighty",
            "link": "RecordLink",
            "percent": 100,
            "hz": " - "
        },
        {
            "user": "WKGames",
            "link": "RecordLink",
            "percent": 100,
            "hz": " - "
        },
        {
            "user": "ZircleZ",
            "link": "RecordLink",
            "percent": 100,
            "hz": " - "
        },
        {
            "user": "wassas1",
            "link": "RecordLink",
            "percent": 100,
            "hz": " - "
        },
        {
            "user": "Soulbound",
            "link": "RecordLink",
            "percent": 100,
            "hz": " - "
        },
        {
            "user": "AceK58",
            "link": "RecordLink",
            "percent": 100,
            "hz": " - "
        },
        {
            "user": "gonker",
            "link": "RecordLink",
            "percent": 100,
            "hz": " - "
        },
        {
            "user": "DarkInfinity286",
            "link": "RecordLink",
            "percent": 100,
            "hz": " - "
        },
        {
            "user": "DaShahzad",
            "link": "RecordLink",
            "percent": 100,
            "hz": " - "
        },
        {
            "user": "Liverlan",
            "link": "RecordLink",
            "percent": 100,
            "hz": " - "
        },
        {
            "user": "yellowbutterflyman", 
            "link": "RecordLink",
            "percent": 100,
            "hz": " - "
        }
    ]
}
