{ 
    "id": 97076118,
    "name": "Ghost Ship",
    "author": "ThanatosGMD",
    "creators": [],
    "verifier": "ThanatosGMD",
    "verification": "https://youtu.be/De5zoK24JQo?si=u83rDep1eQdUZDYt",
    "percentToQualify": 100,
    "records": [
        {
            "user": "Breaker",
            "percent": 100,
            "hz": 60
        },

        {
            "user": "wassas1",
            "percent": 100,
            "hz": 60
        },
        {
            "user": "Sir_Manface",
            "percent": 100,
            "hz": 60
        },
        {
            "user": "scape167",
            "percent": 100,
            "hz": 60
        },
        {
            "user": "WKGames",
            "percent": 100,
            "hz": 60
        },
        {
            "user": "ZircleZ",
            "percent": 100,
            "hz": 60
        },
        {
            "user": "Yoshi",
            "percent": 100,
            "hz": 60
        },
        {
            "user": "DaShahzad",
            "percent": 100,
            "hz": 60
        }
    ]
}
 