{
    "id": 101305905,
    "name": "Hazel",
    "author": "Simwamwi",
    "creators": [],
    "verifier": "Simwamwi",
    "verification": "https://youtu.be/VbK7IcllD_0?si=30hSTTa_fPBWIy_m",
    "percentToQualify": 100,
    "records": [
        {
            "user": "POKEMON GD",
            "percent": 100,
            "hz": 60
        },
        {
            "user": "DIUSED",
            "percent": 100,
            "hz": 60
        },
        {
            "user": "Azulamazigh",
            "percent": 100,
            "hz": 60
        }   
        
    ]
}
