{
    "id": 106467839,
    "name": "Ignited Levitation",
    "author": "Taned777",
    "creators": ["aloom, erquillo1"],
    "verifier": "Taned777",
    "verification": "https://youtu.be/T-T1U7fjbxg?si=JSxxwW1cZQ5UAuIb",
    "desc": "desc",
    "percentToQualify": 100,
    "records": [
        {
            "user": "Taned777",
            "link": "RecordLink",
            "percent": 100,
            "hz": " - "
        },
        {
            "user": "ZircleZ",
            "link": "RecordLink",
            "percent": 100,
            "hz": " - "
        },
        {
            "user": "Breaker",
            "link": "RecordLink",
            "percent": 100,
            "hz": " - "
        },
        {
            "user": "l1ghtning",
            "link": "RecordLink",
            "percent": 100,
            "hz": " - "
        },
        {
            "user": "scape167",
            "link": "RecordLink",
            "percent": 100,
            "hz": " - "
        },
        {
            "user": "WKGames",
            "link": "RecordLink",
            "percent": 100,
            "hz": " - "
        }
    ]
}
