{
    "id": 20511156,
    "name": "Takeoff (D)",
    "author": "nasgubb",
    "creators": [],
    "verifier": "nasgubb",
    "verification": "https://youtu.be/Xy_hVgSELeM?si=YBPT1sOnDjJZXxjX",
    "percentToQualify": "100",
    "password": "152364",
    "records": [
        {
            "user": "kuba",
            "link": "",
            "percent": 100,
            "hz": 120
        },
        {
            "user": "l1ghtning",
            "link": "",
            "percent": 100,
            "hz": 360
        },
        {
            "user": "TMG",
            "link": "",
            "percent": 100,
            "hz": 360
        },
        {
            "user": "Melody",
            "link": "",
            "percent": 100,
            "hz": 144
        },
        {
            "user": "Big",
            "link": "",
            "percent": 100,
            "hz": 144
        },
        {
            "user": "stickch",
            "link": "",
            "percent": 100,
            "hz": "- "
        },
        {
            "user": "Dissmo",
            "link": "",
            "percent": 100,
            "hz": 60
        },
        {
            "user": "DIUS3D",
            "link": "",
            "percent": 100,
            "hz": 120
        },
        {
            "user": "1kb",
            "link": "",
            "percent": 100,
            "hz": "- "
        },
        {
            "user": "Subperfect",
            "link": "",
            "percent": 100,
            "hz": 60
        },
        {
            "user": "Kuzdavo",
            "link": "",
            "percent": 100,
            "hz": 60
        },
        {
            "user": "RoboBear04",
            "link": "",
            "percent": 100,
            "hz": 120
        },
        {
            "user": "DenyZr",
            "link": "",
            "percent": 100,
            "hz": 240
        },
        {
            "user": "TrueJumpy",
            "link": "",
            "percent": 100,
            "hz": "- "
        },
        {
            "user": "Ireane",
            "link": "",
            "percent": 100,
            "hz": "- "
        },
        {
            "user": "Aboim7",
            "link": "",
            "percent": 100,
            "hz": "- "
        },
        {
            "user": "Zorktron",
            "link": "",
            "percent": 100,
            "hz": "- "
        },
        {
            "user": "gusta",
            "link": "",
            "percent": 100,
            "hz": "- "
        },
        {
            "user": "The_AztraL",
            "link": "",
            "percent": 100,
            "hz": 144
        },
        {
            "user": "Redcat",
            "link": "",
            "percent": 100,
            "hz": 120
        },
        {
            "user": "Cosmo",
            "link": "",
            "percent": 100,
            "hz": "- "
        },
        {
            "user": "yzae",
            "link": "",
            "percent": 100,
            "hz": 360
        },
        {
            "user": "zekek",
            "link": "",
            "percent": 100,
            "hz": "- "
        },
        {
            "user": "ToastyNugget",
            "link": "https://youtu.be/55BPxDp6kgE",
            "percent": 100,
            "hz": 165
        },
        {
            "user": "tetrade",
            "link": "",
            "percent": 100,
            "hz": "- "
        },
        {
            "user": "JoacoPe",
            "link": "",
            "percent": 100,
            "hz": 120
        },
        {
            "user": "Arcadie",
            "link": "",
            "percent": 100,
            "hz": 360
        },
        {
            "user": "jaynt",
            "link": "",
            "percent": 100,
            "hz": 240
        },
        {
            "user": "MeowMasterer",
            "link": "",
            "percent": 100,
            "hz": 75
        },
        {
            "user": "mera",
            "link": "",
            "percent": 100,
            "hz": "- "
        },
        {
            "user": "sigmaexe",
            "link": "",
            "percent": 100,
            "hz": "- "
        },
        {
            "user": "1Tric",
            "link": "https://youtu.be/nU6EcDjKj9Y?si=F1OMKjcdFUiLQ7Zt",
            "percent": 100,
            "hz": 360
        },
        {
            "user": "Anomaly",
            "link": "",
            "percent": 100,
            "hz": "- "
        },
        {
            "user": "QuadSecret",
            "link": "",
            "percent": 100,
            "hz": "- "
        },
        {
            "user": "flingus",
            "link": "",
            "percent": 100,
            "hz": 240
        },
        {
            "user": "WKGames",
            "link": "",
            "percent": 100,
            "hz": "- "
        },
        {
            "user": "Plastic",
            "link": "",
            "percent": 100,
            "hz": "- "
        },
        {
            "user": "nukakulah",
            "link": "",
            "percent": 100,
            "hz": 60
        },
        {
            "user": "jkrt2",
            "link": "",
            "percent": 100,
            "hz": 360
        },
        {
            "user": "HamiltonRody",
            "link": "",
            "percent": 100,
            "hz": "- "
        },
        {
            "user": "Scary",
            "link": "https://youtu.be/mrW36avJARc?si=bfkhf8CqhkaEmzqK",
            "percent": 100,
            "hz": "- "
        },
        {
            "user": "niue",
            "link": "",
            "percent": 100,
            "hz": 240
        },
        {
            "user": "htf",
            "link": "",
            "percent": 100,
            "hz": "- "
        },
        {
            "user": "cupcake",
            "link": "",
            "percent": 100,
            "hz": "- "
        },
        {
            "user": "Abeginner",
            "link": "",
            "percent": 100,
            "hz": 240
        },
        {
            "user": "rommydash",
            "link": "",
            "percent": 100,
            "hz": "- "
        },
        {
            "user": "DamoonX",
            "link": "",
            "percent": 100,
            "hz": "- "
        },
        {
            "user": "goody",
            "link": "https://youtu.be/XOhHg1-mEXw?si=8uWHU3CDkOmbiMpq",
            "percent": 100,
            "hz": "- "
        },
        {
            "user": "AerialShard",
            "link": "",
            "percent": 100,
            "hz": 60
        },
        {
            "user": "shenanigans",
            "link": "",
            "percent": 100,
            "hz": 360
        },
        {
            "user": "TheoSi",
            "link": "",
            "percent": 100,
            "hz": "- "
        },
        {
            "user": "Sheepyboy",
            "link": "https://youtu.be/F01JztmZl_s?si=hCRGZ48PyGjtXtrc",
            "percent": 100,
            "hz": "- "
        },
        {
            "user": "Surina",
            "link": "",
            "percent": 100,
            "hz": "- "
        },
        {
            "user": "zzoink15",
            "link": "",
            "percent": 100,
            "hz": "- "
        },
        {
            "user": "nishionary",
            "link": "",
            "percent": 100,
            "hz": "- "
        },
        {
            "user": "Dwibble",
            "link": "",
            "percent": 100,
            "hz": "- "
        },
        {
            "user": "Shiraraxi",
            "link": "",
            "percent": 100,
            "hz": "- "
        },
        {
            "user": "tomm",
            "link": "",
            "percent": 100,
            "hz": 240
        },
        {
            "user": "Subw1",
            "link": "",
            "percent": 100,
            "hz": "- "
        },
        {
            "user": "500skills",
            "link": "",
            "percent": 100,
            "hz": "- "
        },
        {
            "user": "ZircleZ",
            "link": "",
            "percent": 100,
            "hz": "- "
        },
        {
            "user": "Chahnkeh",
            "link": "",
            "percent": 100,
            "hz": "- "
        },
        {
            "user": "POKEMON GD",
            "link": "",
            "percent": 100,
            "hz": "- "
        },
        {
            "user": "scape167",
            "link": "",
            "percent": 100,
            "hz": "- "
        },
        {
            "user": "gonkergd",
            "link": "",
            "percent": 100,
            "hz": 144
        },
        {
            "user": "Yefan",
            "link": "",
            "percent": 100,
            "hz": "- "
        },
        {
            "user": "SkyHigh",
            "link": "",
            "percent": 100,
            "hz": "- "
        },
        {
            "user": "StellarGradient",
            "link": "",
            "percent": 100,
            "hz": "- "
        },
        {
            "user": "ThayLoser",
            "link": "",
            "percent": 100,
            "hz": "- "
        },
        {
            "user": "CraZeL",
            "link": "",
            "percent": 100,
            "hz": "- "
        },
        {
            "user": "dashy6283",
            "link": "",
            "percent": 100,
            "hz": "- "
        },
        {
            "user": "Excryst",
            "link": "",
            "percent": 100,
            "hz": "- "
        },
        {
            "user": "shiver",
            "link": "",
            "percent": 100,
            "hz": "- "
        },
        {
            "user": "Music addict",
            "link": "",
            "percent": 100,
            "hz": "- "
        },
        {
            "user": "DaShahzad",
            "link": "",
            "percent": 100,
            "hz": "- "
        },
        {
            "user": "Etoile speed",
            "link": "",
            "percent": 100,
            "hz": "- "
        },
        {
            "user": "pat",
            "link": "",
            "percent": 100,
            "hz": "- "
        },
        {
            "user": "Speedbreaker",
            "link": "https://youtu.be/2A6yVFqMTxs?si=Y5LUvc-o5eMxO_cr",
            "percent": 100,
            "hz": "- "
        },
        {
            "user": "CoreyDoor",
            "link": "",
            "percent": 100,
            "hz": "- "
        },
        {
            "user": "Jarzst",
            "link": "",
            "percent": 100,
            "hz": "- "
        },
        {
            "user": "IzayoiHSH",
            "link": "",
            "percent": 100,
            "hz": "- "
        },
        {
            "user": "guyyyy8223",
            "link": "",
            "percent": 100,
            "hz": 60
        },
        {
            "user": "carso",
            "link": "",
            "percent": 100,
            "hz": "- "
        },
        {
            "user": "bonezizdum",
            "link": "",
            "percent": 100,
            "hz": "- "
        },
        {
            "user": "MrPoopyBurger",
            "link": "",
            "percent": 100,
            "hz": "- "
        },
        {
            "user": "CoriOshawott",
            "link": "",
            "percent": 100,
            "hz": "- "
        },
        {
            "user": "MjNinja",
            "link": "",
            "percent": 100,
            "hz": "- "
        },
        {
            "user": "DarkInfinity286",
            "link": "",
            "percent": 100,
            "hz": "- "
        },
        {
            "user": "xyne",
            "link": "",
            "percent": 100,
            "hz": "- "
        },
        {
            "user": "krii",
            "link": "",
            "percent": 100,
            "hz": "- "
        },
        {
            "user": "Sir_Manface",
            "link": "",
            "percent": 100,
            "hz": "- "
        },
        {
            "user": "Bladey",
            "percent": 100,
            "hz": 60
        },
        {
            "user": "Identity",
            "percent": 100,
            "hz": 60
        },
        {
            "user": "huggies",
            "percent": 100,
            "hz": 60
        },
        {
            "user": "LifelessComputer",
            "percent": 100,
            "hz": "- "
        }
    ]
}
